

[
    {
        "transactionId": "alsodo1i2nod" ,
        "transactionDate": "2022-01-01",
        "transactionMonth": "January",
        "confirmations" : {
            "sender" : "yes",
            "receiver" : "no"
        }
    },
    {
        "transactionId": "092380alsdcaoi",
        "transactionDate": "2022-01-01",
        "transactionMonth": "January",
        "confirmations" : {
            "sender" : "no",
            "receiver" : "no"
        }
    },
    {
        "transactionId": "a239c0n990",
        "transactionDate": "2022-01-01",
        "transactionMonth": "Februaray",
        "confirmations" : {
            "sender" : "yes",
            "receiver" : "no"
        }
    },
    {
        "transactionId": "921dsacjnaec12",
        "transactionDate": "2022-01-01",
        "transactionMonth": "Februaray",
        "confirmations" : {
            "sender" : "yes",
            "receiver" : "yes"
        }
    },
    {
        "transactionId": "123jakscineian",
        "transactionDate": "2022-01-01",
        "transactionMonth": "Februaray",
        "confirmations" : {
            "sender" : "yes",
            "receiver" : "yes"
        }
    },
    {
        "transactionId": "192cajscdie23",
        "transactionDate": "2022-01-01",
        "transactionMonth": "Februaray",
        "confirmations" : {
            "sender" : "yes",
            "receiver" : "yes"
        }
    },
    {
        "transactionId": "9823hksdanfna3",
        "transactionDate": "2022-01-01",
        "transactionMonth": "Februaray",
        "confirmations" : {
            "sender" : "yes",
            "receiver" : "yes"
        }
    },
    {
        "transactionId": "123sddacweda12",
        "transactionDate": "2022-01-01",
        "transactionMonth": "Februaray",
        "confirmations" : {
            "sender" : "yes",
            "receiver" : "no"
        }
    },
    {
        "transactionId": "afsce2331231",
        "transactionDate": "2022-01-01",
        "transactionMonth": "March",
        "confirmations" : {
            "sender" : "yes",
            "receiver" : "yes"
        }
    },
    {
        "transactionId": "caejclknk2121",
        "transactionDate": "2022-01-01",
        "transactionMonth": "March",
        "confirmations" : {
            "sender" : "yes",
            "receiver" : "yes"
        }
    },
    {
        "transactionId": "399uasdnkacne",
        "transactionDate": "2022-01-01",
        "transactionMonth": "Februaray",  
        "confirmations" : {
            "sender" : "yes",
            "receiver" : "no"
        }
    }
]